symbiont/__init__.py
symbiont/components.py
symbiont/injector.py
symbiont-0.1.1.dist-info/LICENSE
symbiont-0.1.1.dist-info/METADATA
symbiont-0.1.1.dist-info/WHEEL
symbiont-0.1.1.dist-info/RECORD
