Metadata-Version: 2.1
Name: symbiont
Version: 0.1.1
Summary: Tiny module-service and dependency injection framework
Author: Ivan Borisenko
Author-email: contact@13g10n.com
Requires-Python: >=3.8,<4.0
Classifier: Programming Language :: Python :: 3
Classifier: Programming Language :: Python :: 3.8
Classifier: Programming Language :: Python :: 3.9
Classifier: Programming Language :: Python :: 3.10
Classifier: Programming Language :: Python :: 3.11
